gfmscraper/__init__.py
gfmscraper/scraper.py
gfmscraper-0.3.0.dist-info/LICENSE
gfmscraper-0.3.0.dist-info/METADATA
gfmscraper-0.3.0.dist-info/WHEEL
gfmscraper-0.3.0.dist-info/top_level.txt
gfmscraper-0.3.0.dist-info/RECORD
