Metadata-Version: 2.1
Name: gfmscraper
Version: 0.3.0
Summary: A small library to scrap GoFundMe campaigns.
Home-page: https://github.com/PalestinianVoices/GoFundMeScrapper
Author: Ziad A. & Essam W.
License: MIT
Classifier: Intended Audience :: Developers
Classifier: License :: OSI Approved :: MIT License
Classifier: Programming Language :: Python
Classifier: Programming Language :: Python :: 3
Classifier: Programming Language :: Python :: 3.6
Classifier: Programming Language :: Python :: 3.7
Classifier: Programming Language :: Python :: 3.8
Classifier: Programming Language :: Python :: 3.9
Classifier: Operating System :: OS Independent
License-File: LICENSE
Requires-Dist: requests
Requires-Dist: bs4
